dbt/adapters/singlestore/__init__.py
dbt/adapters/singlestore/__version__.py
dbt/adapters/singlestore/column.py
dbt/adapters/singlestore/connections.py
dbt/adapters/singlestore/impl.py
dbt/adapters/singlestore/relation.py
dbt/include/singlestore/__init__.py
dbt/include/singlestore/dbt_project.yml
dbt/include/singlestore/profile_template.yml
dbt/include/singlestore/sample_profiles.yml
dbt/include/singlestore/macros/catalog.sql
dbt/include/singlestore/macros/columns.sql
dbt/include/singlestore/macros/common.sql
dbt/include/singlestore/macros/grants.sql
dbt/include/singlestore/macros/metadata.sql
dbt/include/singlestore/macros/materializations/view.sql
dbt/include/singlestore/macros/materializations/incremental/incremental.sql
dbt/include/singlestore/macros/materializations/snapshot/helpers.sql
dbt/include/singlestore/macros/materializations/snapshot/snapshot.sql
dbt/include/singlestore/macros/materializations/snapshot/snapshot_merge.sql
dbt/include/singlestore/macros/materializations/snapshot/strategies.sql
dbt/include/singlestore/macros/utils/bool_or.sql
dbt/include/singlestore/macros/utils/cast_bool_to_text.sql
dbt/include/singlestore/macros/utils/data_types.sql
dbt/include/singlestore/macros/utils/dateadd.sql
dbt/include/singlestore/macros/utils/datediff.sql
dbt/include/singlestore/macros/utils/hash.sql
dbt/include/singlestore/macros/utils/listagg.sql
dbt/include/singlestore/macros/utils/safe_cast.sql
dbt/include/singlestore/macros/utils/split_part.sql
dbt/include/singlestore/macros/utils/timestamps.sql
dbt_singlestore-1.9.0.dist-info/licenses/LICENSE
dbt_singlestore-1.9.0.dist-info/METADATA
dbt_singlestore-1.9.0.dist-info/WHEEL
dbt_singlestore-1.9.0.dist-info/entry_points.txt
dbt_singlestore-1.9.0.dist-info/top_level.txt
dbt_singlestore-1.9.0.dist-info/RECORD
