Metadata-Version: 2.4
Name: dbt-singlestore
Version: 1.9.0
Summary: The singlestore adapter plugin for dbt
Home-page: https://github.com/memsql/dbt-singlestore
Author: SingleStore Inc.
Author-email: support@singlestore.com
License: Apache License 2.0
License-File: LICENSE
Requires-Dist: dbt-adapters<2.0.0,>=1.0.0
Requires-Dist: dbt-core>=1.8
Requires-Dist: singlestoredb==1.15.8
Requires-Dist: dataclasses_json>=0.5.6
Dynamic: author
Dynamic: author-email
Dynamic: description
Dynamic: home-page
Dynamic: license
Dynamic: license-file
Dynamic: requires-dist
Dynamic: summary
